{"model_type": "regression", "training_label": "score", "training_timestamp": "2019-10-08 09:45:53", "model": {"class": "<class 'sklearn.ensemble.forest.RandomForestRegressor'>", "params": {"bootstrap": true, "criterion": "mse", "max_depth": null, "max_features": "auto", "max_leaf_nodes": null, "min_impurity_decrease": 0.0, "min_impurity_split": null, "min_samples_leaf": 1, "min_samples_split": 2, "min_weight_fraction_leaf": 0.0, "n_estimators": 300, "n_jobs": null, "oob_score": true, "random_state": null, "verbose": 0, "warm_start": false}}, "oob_score": "0.73", "training_data_shape": [3795, 7], "filepath": "/Users/keith.cheveralls/Box/KCC-box-projects/confluency-annotator/models/2019-10-08/training_data.csv"}